log_manager/__init__.py
log_manager/db_logger.py
log_manager/log_manager.py
log_manager/typeclass/__init__.py
log_manager/typeclass/logging_operations.py
batch_log_manager-0.1.1.dist-info/METADATA
batch_log_manager-0.1.1.dist-info/WHEEL
batch_log_manager-0.1.1.dist-info/top_level.txt
batch_log_manager-0.1.1.dist-info/RECORD
