Metadata-Version: 2.2
Name: batch-log-manager
Version: 0.1.1
Summary: A Python package for managing logs.
Home-page: https://github.com/OpenJ92/log-manager
Author: Jacob Vartuli-Schonberg
Author-email: jacob.vartuli.92@gmail.com
Classifier: Programming Language :: Python :: 3
Classifier: License :: OSI Approved :: MIT License
Classifier: Operating System :: OS Independent
Requires-Python: >=3.9
Dynamic: author
Dynamic: author-email
Dynamic: classifier
Dynamic: description
Dynamic: description-content-type
Dynamic: home-page
Dynamic: requires-python
Dynamic: summary
